DESCRIPTION.rst
MANIFEST.in
README.rst
setup.cfg
setup.py
montepetro/__init__.py
montepetro/generators.py
montepetro/json_parser.py
montepetro/models.py
montepetro/properties.py
montepetro/regions.py
montepetro/seed_generators.py
montepetro/utils.py
montepetro.egg-info/PKG-INFO
montepetro.egg-info/SOURCES.txt
montepetro.egg-info/dependency_links.txt
montepetro.egg-info/requires.txt
montepetro.egg-info/top_level.txt