Metadata-Version: 1.1
Name: montepetro
Version: 0.3.6
Summary: Probabilistic Reserve Estimates in Python
Home-page: https://github.com/LukasMosser/MontePetro
Author: Lukas Mosser
Author-email: lukas.mosser@gmail.com
License: GPL
Download-URL: https://github.com/LukasMosser/MontePetro/tarball/0.3.6
Keywords: montecarlo,probabilistic,oil,gas
Platform: UNKNOWN
